vizdantic/__init__.py
vizdantic/adapter.py
vizdantic/cli.py
vizdantic/render.py
vizdantic/schema.py
vizdantic/skill_install.py
vizdantic/spec.py
vizdantic/validate.py
vizdantic/plugins/plotly.py
skills/vizdantic-runner/SKILL.md
skills/vizdantic-runner/references/theme-quickstart.json
skills/vizdantic-runner/references/vizdantic-spec-quickref.md
skills/vizdantic-runner/scripts/render_viz.py
vizdantic-0.2.2.dist-info/METADATA
vizdantic-0.2.2.dist-info/WHEEL
vizdantic-0.2.2.dist-info/entry_points.txt
vizdantic-0.2.2.dist-info/licenses/LICENSE
vizdantic-0.2.2.dist-info/RECORD
