Metadata-Version: 2.4
Name: vizdantic
Version: 0.2.2
Summary: Schema-first visualization specifications for LLMs
Author: Ivo Garais
License: MIT
License-File: LICENSE
Classifier: Development Status :: 3 - Alpha
Classifier: Intended Audience :: Developers
Classifier: License :: OSI Approved :: MIT License
Classifier: Programming Language :: Python :: 3
Classifier: Programming Language :: Python :: 3 :: Only
Classifier: Programming Language :: Python :: 3.10
Classifier: Topic :: Scientific/Engineering :: Visualization
Classifier: Topic :: Software Development :: Libraries
Requires-Python: >=3.10
Requires-Dist: pydantic>=2.11
Provides-Extra: dev
Requires-Dist: kaleido>=0.2; extra == 'dev'
Requires-Dist: pandas>=2.0; extra == 'dev'
Requires-Dist: plotly>=5.0; extra == 'dev'
Requires-Dist: pyyaml>=6.0; extra == 'dev'
Provides-Extra: plotly
Requires-Dist: plotly>=5.0; extra == 'plotly'
